.pypirc
HISTORY.txt
MANIFEST.in
README.rst
distribute-0.6.24.tar.gz
setup.py
test
experimental/__init__.py
experimental.pythonpackages.egg-info/PKG-INFO
experimental.pythonpackages.egg-info/SOURCES.txt
experimental.pythonpackages.egg-info/dependency_links.txt
experimental.pythonpackages.egg-info/top_level.txt
experimental/pythonpackages/__init__.py