Metadata-Version: 1.0
Name: experimental.pythonpackages
Version: 0.3.6
Summary: Test
Home-page: UNKNOWN
Author: UNKNOWN
Author-email: UNKNOWN
License: UNKNOWN
Platform: UNKNOWN
